Workbook

Sheet Master - Reference
A2: Database: | B2: Medical Information Mart for Intensive Care
C6: SCHEMA NAME | D6: ATTRIBUTE NAMES | E6: DESCRIPTION
C7: A_CHARTDURATIONS | D7: SUBJECT_ID,ICUSTAY_ID,ITEMID,ELEMID,STARTTIME,STARTREALTIME,ENDTIME,CUID,DURATION | E7: =A_CHARTDURATIONS!B4 -> Patient medical chart data is recorded in the chartevents, d chartitems, a chartdurations and formevents tables
C8: ADDITIVES | D8: SUBJECT_ID,ICUSTAY_ID,ITEMID,IOITEMID,CHARTTIME,ELEMID,CGID,CUID,AMOUNT,DOSEUNITS,ROUTE | E8: =ADDITIVES!B4 -> Patient input/output (IO) data is recorded in the ioevents, d ioitems, a iodurations, deliveries, totalbalevents and additives tables.
C9: ADMISSIONS | D9: HADM_ID,SUBJECT_ID,ADMIT_DT,DISCH_DT | E9: =ADMISSIONS!B4 -> The ADMISSIONS table gives information regarding a patient’s admission to the hospital. Since each unique hospital visit for a patient is assigned a unique HADM_ID, the ADMISSIONS table can be considered as a definition table for HADM_ID. Information available includes timing information for admission and discharge, demographic information, the source of the admission, and so on
C10: A_IODURATIONS | D10: SUBJECT_ID,ICUSTAY_ID,ITEMID,ELEMID,STARTTIME,STARTREALTIME,ENDTIME,CUID,DURATION | E10: =A_IODURATIONS!B4 -> Patients Input / Output event and its time. Example : Type of IV infusions provided to a patient during their ICU stay and start and End time of the IV event
C11: A_MEDDURATIONS | D11: SUBJECT_ID,ICUSTAY_ID,ITEMID,ELEMID,STARTTIME,STARTREALTIME,ENDTIME,CUID,DURATION | E11: =A_MEDDURATIONS!B4 -> Medication(s) given to a patient are recorded in this table. Example: If a patient is with calcium deficiencies then thru IV infusion method Medication "Calcium Gluconate" will get infused. Here medication refers to the drugs given to the patient
C12: CENSUSEVENTS | D12: CENSUS_ID,SUBJECT_ID,INTIME,OUTTIME,CAREUNIT,DESTCAREUNIT,DISCHSTATUS,LOS,ICUSTAY_ID | E12: =CENSUSEVENTS!B4 -> Each time a patient enters or leaves a particular care unit, an event is recorded into the database in the table censusevents. Each of these events (identified by the column census id), contain the time and date of entrance and exit of the care unit, the current unit the patient was hosted, the destination care unit the patient was transferred to, and the length of stay in the ICU room for that particular event.
C13: CHARTEVENTS | D13: SUBJECT_ID,ICUSTAY_ID,ITEMID,CHARTTIME,ELEMID,REALTIME,CGID,CUID,VALUE1,VALUE1NUM,VALUE1UOM,VALUE2,VALUE2NUM,VALUE2UOM,RESULTSTATUS,STOPPED | E13: =CHARTEVENTS!B4 -> CHARTEVENTS contains all the charted data available for a patient. During their ICU stay, the primary repository of a patient’s information is their electronic chart. The electronic chart displays patients’ routine vital signs and any additional information relevant to their care: ventilator settings, laboratory values, code status, mental status, and so on. As a result, the bulk of information about a patient’s stay is contained in CHARTEVENTS. Furthermore, even though laboratory values are captured elsewhere (LABEVENTS), they are frequently repeated within CHARTEVENTS. This occurs because it is desirable to display the laboratory values on the patient’s electronic chart, and so the values are copied from the database storing laboratory values to the database storing the CHARTEVENTS.
C14: COMORBIDITY_SCORES | D14: SUBJECT_ID,HADM_ID,CATEGORY,CONGESTIVE_HEART_FAILURE,CARDIAC_ARRHYTHMIAS,VALVULAR_DISEASE,PULMONARY_CIRCULATION,PERIPHERAL_VASCULAR,HYPERTENSION,PARALYSIS,OTHER_NEUROLOGICAL,CHRONIC_PULMONARY,DIABETES_UNCOMPLICATED,DIABETES_COMPLICATED,HYPOTHYROIDISM,RENAL_FAILURE,LIVER_DISEASE,PEPTIC_ULCER,AIDS,LYMPHOMA,METASTATIC_CANCER,SOLID_TUMOR,RHEUMATOID_ARTHRITIS,COAGULOPATHY,OBESITY,WEIGHT_LOSS,FLUID_ELECTROLYTE,BLOOD_LOSS_ANEMIA,DEFICIENCY_ANEMIAS,ALCOHOL_ABUSE,DRUG_ABUSE,PSYCHOSES,DEPRESSION | E14: =COMORBIDITY_SCORES!B4 -> Patient Comorbidity index for all the secondary disease along with primary
C15: DELIVERIES | D15: SUBJECT_ID,ICUSTAY_ID,IOITEMID,CHARTTIME,ELEMID,CGID,CUID,SITE,RATE,RATEUOM | E15: =DELIVERIES!B4 -> Its related to the I/O Events and the details in the table indicates that the rate at which the medication has infused to the patient. Example: D5W (Dextrose) is a form of glucose can be infused to the patients depends on their health condition such as 10 ml/hr or 18.5 ml/hr, etc.,
C16: DEMOGRAPHIC_DETAIL | D16: SUBJECT_ID,HADM_ID,MARITAL_STATUS_ITEMID,MARITAL_STATUS_DESCR,ETHNICITY_ITEMID,ETHNICITY_DESCR,OVERALL_PAYOR_GROUP_ITEMID,OVERALL_PAYOR_GROUP_DESCR,RELIGION_ITEMID,RELIGION_DESCR,ADMISSION_TYPE_ITEMID,ADMISSION_TYPE_DESCR,ADMISSION_SOURCE_ITEMID,ADMISSION_SOURCE_DESCR | E16: =DEMOGRAPHIC_DETAIL!B4 -> Patients demographic details. This details will be captured at the time of admission to any Care units
C17: DEMOGRAPHICEVENTS | D17: SUBJECT_ID,HADM_ID,ITEMID | E17: =DEMOGRAPHICEVENTS!B4 -> Additional demographic details about the patient such as "Admisison source - HMO referal, Religion - Patient denied to provide, Payor group name - Auto liability, etc.,"
C18: D_PATIENTS | D18: SUBJECT_ID,SEX,DOB,DOD,HOSPITAL_EXPIRE_FLG | E18: =D_PATIENTS!B4 -> Defines each SUBJECT_ID in the database, i.e. defines a single patient.
C19: DRGEVENTS | D19: SUBJECT_ID,HADM_ID,ITEMID,COST_WEIGHT | E19: =DRGEVENTS!B4 -> Drug Related Group is a patient classification system that standardizes prospective payment to hospitals and encourages cost containment initiatives.
C20: ICD9 | D20: SUBJECT_ID,HADM_ID,SEQUENCE,CODE,DESCRIPTION | E20: ='ICD9'!B4 -> Patients diagnosis event details. Example : Diagnosis test related "Iron Deficiency Anemia", etc.,
C21: ICUSTAY_DAYS | D21: ICUSTAY_ID,SUBJECT_ID,SEQ,BEGINTIME,ENDTIME,FIRST_DAY_FLG,LAST_DAY_FLG | E21: =ICUSTAY_DAYS!B4 -> Patients Care unit stay details. Mostly this table helps to calculate total number of care unit stay for a given patient with help of "First" and "Last" day flag(Y/N)
C22: ICUSTAY_DETAIL | D22: ICUSTAY_ID,SUBJECT_ID,GENDER,DOB,DOD,EXPIRE_FLG,SUBJECT_ICUSTAY_TOTAL_NUM,SUBJECT_ICUSTAY_SEQ,HADM_ID,HOSPITAL_TOTAL_NUM,HOSPITAL_SEQ,HOSPITAL_FIRST_FLG,HOSPITAL_LAST_FLG,HOSPITAL_ADMIT_DT,HOSPITAL_DISCH_DT,HOSPITAL_LOS,HOSPITAL_EXPIRE_FLG,ICUSTAY_TOTAL_NUM,ICUSTAY_SEQ,ICUSTAY_FIRST_FLG,ICUSTAY_LAST_FLG,ICUSTAY_INTIME,ICUSTAY_OUTTIME,ICUSTAY_ADMIT_AGE,ICUSTAY_AGE_GROUP,ICUSTAY_LOS,ICUSTAY_EXPIRE_FLG,ICUSTAY_FIRST_CAREUNIT,ICUSTAY_LAST_CAREUNIT,ICUSTAY_FIRST_SERVICE,ICUSTAY_LAST_SERVICE,HEIGHT,WEIGHT_FIRST,WEIGHT_MIN,WEIGHT_MAX,SAPSI_FIRST,SAPSI_MIN,SAPSI_MAX,SOFA_FIRST,SOFA_MIN,SOFA_MAX,MATCHED_WAVEFORMS_NUM | E22: =ICUSTAY_DETAIL!B4 -> Patients care Unit event details. This table will contains hospital admission, discharged, Care unit Admission, discharged, patients age, date of death, etc.,
C23: ICUSTAYEVENTS | D23: ICUSTAY_ID,SUBJECT_ID,INTIME,OUTTIME,LOS,FIRST_CAREUNIT,LAST_CAREUNIT | E23: =ICUSTAYEVENTS!B4 -> Patients Care unit stay details are captured in a single line. This table will provide an overview of the patients care unit stay such as "Admission date, discharged date, length of stay, Care unit at the time of admission and discharged, etc.,"
C24: IOEVENTS | D24: SUBJECT_ID,ICUSTAY_ID,ITEMID,CHARTTIME,ELEMID,ALTID,REALTIME,CGID,CUID,VOLUME,VOLUMEUOM,UNITSHUNG,UNITSHUNGUOM,NEWBOTTLE,STOPPED,ESTIMATE | E24: =IOEVENTS!B4 -> Patients Input / Output event during their Care unit stay. Example : Type of IV infusions provided to a patient during their ICU stay and start and End time of the IV event
C25: LABEVENTS | D25: SUBJECT_ID,HADM_ID,ICUSTAY_ID,ITEMID,CHARTTIME,VALUE,VALUENUM,FLAG,VALUEUOM | E25: =LABEVENTS!B4 -> The LABEVENTS data contains information regarding laboratory based measurements. The process for acquiring a lab measurement is as follows: first, a member of the clinical staff acquires a fluid from a site in the patient’s body (e.g. blood from an arterial line, urine from a catheter, etc). Next, the fluid is bar coded to associate it with the patient and timestamped to record the time of the fluid acquisition. The lab analyses the data and returns a result within 4-12 hours.
C26: MEDEVENTS | D26: SUBJECT_ID,ICUSTAY_ID,ITEMID,CHARTTIME,ELEMID,REALTIME,CGID,CUID,VOLUME,DOSE,DOSEUOM,SOLUTIONID,SOLVOLUME,SOLUNITS,ROUTE,STOPPED | E26: =MEDEVENTS!B4 -> Medication(s) given to a patient are recorded in this table.
C27: MICROBIOLOGYEVENTS | D27: SUBJECT_ID,HADM_ID,CHARTTIME,SPEC_ITEMID,ORG_ITEMID,ISOLATE_NUM,AB_ITEMID,DILUTION_AMOUNT,DILUTION_COMPARISON,INTERPRETATION | E27: =MICROBIOLOGYEVENTS!B4 -> This table Contains microbiology information, including tests performed and sensitivities
C28: NOTEEVENTS | D28: SUBJECT_ID,HADM_ID,ICUSTAY_ID,ELEMID,CHARTTIME,REALTIME,CGID,CORRECTION,CUID,CATEGORY,TITLE,TEXT,EXAM_NAME,PATIENT_INFO | E28: =NOTEEVENTS!B4 -> Clinical Notes for the patients. Usually during the stay in the Care unit, skilled Nurse / Physician will leave a note about the patients health condition. Sometime, critical health information about patients such as Mortaility event, Comorbidity condition, infections,etc. will be captured in the notes
C29: POE_MED | D29: POE_ID,DRUG_TYPE,DRUG_NAME,DRUG_NAME_GENERIC,PROD_STRENGTH,FORM_RX,DOSE_VAL_RX,DOSE_UNIT_RX,FORM_VAL_DISP,FORM_UNIT_DISP,DOSE_VAL_DISP,DOSE_UNIT_DISP,DOSE_RANGE_OVERRIDE | E29: =POE_MED!B4 -> Pharmacy provider order entry (Pharmacy claims) - The medication and the dosage details are captured from the pharmacy
C30: POE_ORDER | D30: POE_ID,SUBJECT_ID,HADM_ID,ICUSTAY_ID,START_DT,STOP_DT,ENTER_DT,MEDICATION,PROCEDURE_TYPE,STATUS,ROUTE,FREQUENCY,DISPENSE_SCHED,IV_FLUID,IV_RATE,INFUSION_TYPE,SLIDING_SCALE,DOSES_PER_24HRS,DURATION,DURATION_INTVL,EXPIRATION_VAL,EXPIRATION_UNIT,EXPIRATION_DT,LABEL_INSTR,ADDITIONAL_INSTR,MD_ADD_INSTR,RNURSE_ADD_INSTR | E30: =POE_ORDER!B4 -> Pharmacy provider order entry (Pharmacy claims) - The medication and the dosage details are captured from the pharmacy - Detailed version of the data captured based on the usage.All the fields are related to POE_MED table
C31: PROCEDUREEVENTS | D31: SUBJECT_ID,HADM_ID,ITEMID,SEQUENCE_NUM,PROC_DT | E31: =PROCEDUREEVENTS!B4 -> Medical Procedure performed to the patients durign their stay. Procedure (Knee Arthroscopy, Oint Biopsy, etc.,) can be performed either prior or after the diagnosis result
C32: TOTALBALEVENTS | D32: SUBJECT_ID,ICUSTAY_ID,ITEMID,CHARTTIME,ELEMID,REALTIME,CGID,CUID,PERVOLUME,CUMVOLUME,ACCUMPERIOD,APPROX,RESET,STOPPED | E32: =TOTALBALEVENTS!B4 -> Total Fluid balance event

Sheet A_CHARTDURATIONS
A2: Table Name: | D2: A_CHARTDURATIONS
A3: Description
B4: Patient medical chart data is recorded in the chartevents, d chartitems, a chartdurations and formevents tables
C10: Column Name | D10: Data Type | E10: Nullable | F10: Default value | G10: Comments
C11: SUBJECT ID | D11: NUMBER | E11: N | G11: The patient for the chart event
C12: ITEMID | D12: NUMBER | E12: N | G12: The chart item for the duration record
C13: ELEMID | D13: NUMBER | E13: N
C14: STARTTIME | D14: DATE | E14: N | G14: The start time of the chart item
C15: STARTREALTIME | D15: DATE | E15: Y
C16: ENDTIME | D16: DATE | E16: Y | G16: The end time of the chart item
C17: CUID | D17: NUMBER | E17: Y | G17: The care unit where the chart event took place
C18: DURATION | D18: NUMBER | E18: Y | G18: The duration of the chart event

Sheet ADDITIVES
A2: Table Name: | D2: ADDITIVES
A3: Description
B4: Patient input/output (IO) data is recorded in the ioevents, d ioitems, a iodurations, deliveries, totalbalevents and additives tables.
C10: Column Name | D10: Data Type | E10: Nullable | F10: Default value | G10: Comments
C11: SUBJECT ID | D11: NUMBER | E11: N
C12: ITEMID | D12: NUMBER | E12: N
C13: IOITEMID | D13: NUMBER | E13: N
C14: CHARTTIME | D14: DATE | E14: N
C15: ELEMID | D15: NUMBER | E15: N
C16: CGID | D16: NUMBER | E16: Y
C17: CUID | D17: NUMBER | E17: Y
C18: AMOUNT | D18: NUMBER | E18: Y
C19: DOSEUNITS | D19: VARCHAR2 | E19: Y
C20: MLPERUNIT | D20: NUMBER | E20: Y
C21: ROUTE | D21: VARCHAR2 | E21: Y

Sheet ADMISSIONS
A2: Table Name: | D2: ADMISSIONS
A3: Description
B4: The ADMISSIONS table gives information regarding a patient’s admission to the hospital. Since each unique hospital visit for a patient is assigned a unique HADM_ID, the ADMISSIONS table can be considered as a definition table for HADM_ID. Information available includes timing information for admission and discharge, demographic information, the source of the admission, and so on
C10: Column Name | D10: Data Type | E10: Nullable | F10: Default value | G10: Comments
C11: HADM ID | D11: NUMBER | E11: N | G11: Table record unique identier, the hospital admission ID
C12: SUBJECT ID | D12: NUMBER | E12: N | G12: The patient for the admission.
C13: ADM DT | D13: DATE | E13: N | G13: Date and time the patient was admitted to the ICU
C14: DISCH DT | D14: DATE | E14: N | G14: Date and time the patient charged ICU
C15: EXPIRE FLG | D15: CHAR | E15: N | F15: N'

Sheet A_IODURATIONS
A2: Table Name: | D2: A_IODURATIONS
A3: Description
B4: Patients Input / Output event and its time. Example : Type of IV infusions provided to a patient during their ICU stay and start and End time of the IV event
C10: Column Name | D10: Data Type | E10: Nullable | F10: Default value | G10: Comments
C11: SUBJECT ID | D11: NUMBER | E11: N | G11: The patient for the IO event.
C12: ITEMID | D12: NUMBER | E12: N | G12: The IO item for the duration record
C13: ELEMID | D13: NUMBER | E13: N
C14: STARTTIME | D14: DATE | E14: N | G14: The start time of the IO event
C15: STARTREALTIME | D15: DATE | E15: Y
C16: ENDTIME | D16: DATE | E16: Y | G16: The end time of the IO event
C17: CUID | D17: NUMBER | E17: Y | G17: The care unit where the IO event took place (MICU, CCU, NICU, etc.,)
C18: DURATION | D18: NUMBER | E18: Y | G18: The duration of the IO event

Sheet A_MEDDURATIONS
A2: Table Name: | D2: A_MEDDURATIONS
A3: Description
B4: Medication(s) given to a patient are recorded in this table. Example: If a patient is with calcium deficiencies then thru IV infusion method Medication "Calcium Gluconate" will get infused. Here medication refers to the drugs given to the patient
C10: Column Name | D10: Data Type | E10: Nullable | F10: Default value | G10: Comments
C11: SUBJECT ID | D11: NUMBER | E11: N | G11: The patient for the medication
C12: ITEMID | D12: NUMBER | E12: N | G12: The medication item for duration record
C13: ELEMID | D13: NUMBER | E13: N
C14: STARTTIME | D14: DATE | E14: N | G14: The start time of the medication event
C15: STARTREALTIME | D15: DATE | E15: Y
C16: ENDTIME | D16: DATE | E16: Y | G16: The end time of the medication event
C17: CUID | D17: NUMBER | E17: Y | G17: The care unit where the medication event place
C18: DURATION | D18: NUMBER | E18: Y | G18: The duration of the medication event

Sheet CENSUSEVENTS
A2: Table Name: | D2: CENSUSEVENTS
A3: Description
B4: Each time a patient enters or leaves a particular care unit, an event is recorded into the database in the table censusevents. Each of these events (identified by the column census id), contain the time and date of entrance and exit of the care unit, the current unit the patient was hosted, the destination care unit the patient was transferred to, and the length of stay in the ICU room for that particular event.
C10: Column Name | D10: Data Type | E10: Nullable | F10: Default value | G10: Comments
C11: CENSUS ID | D11: NUMBER | E11: N | G11: Table record unique identier, the census event id.
C12: SUBJECT ID | D12: NUMBER | E12: N | G12: The partient for the census event.
C13: INTIME | D13: DATE | E13: N | G13: The time when the patient entered the ICU.
C14: OUTTIME | D14: DATE | E14: Y | G14: The time when the patient left the ICU.
C15: CAREUNIT | D15: NUMBER | E15: Y | G15: The originating care unit for the event.
C16: DESTCAREUNIT | D16: NUMBER | E16: Y | G16: The destination ICU
C17: DISCHSTATUS | D17: VARCHAR2 | E17: Y | G17: The discharge status of the patient
C18: LOS | D18: NUMBER | E18: Y

Sheet CHARTEVENTS
A2: Table Name: | D2: CHARTEVENTS
A3: Description
B4: CHARTEVENTS contains all the charted data available for a patient. During their ICU stay, the primary repository of a patient’s information is their electronic chart. The electronic chart displays patients’ routine vital signs and any additional information relevant to their care: ventilator settings, laboratory values, code status, mental status, and so on. As a result, the bulk of information about a patient’s stay is contained in CHARTEVENTS. Furthermore, even though laboratory values are captured elsewhere (LABEVENTS), they are frequently repeated within CHARTEVENTS. This occurs because it is desirable to display the laboratory values on the patient’s electronic chart, and so the values are copied from the database storing laboratory values to the database storing the CHARTEVENTS.
C10: Column Name | D10: Data Type | E10: Nullable | F10: Default value | G10: Comments
C11: SUBJECT ID | D11: NUMBER | E11: N | G11: The patient for the chart event.
C12: ITEMID | D12: NUMBER | E12: N | G12: The chart item for the event record.
C13: CHARTTIME | D13: DATE | E13: N | G13: The time of the chart event.
C14: ELEMID | D14: NUMBER | E14: N
C15: REALTIME | D15: DATE | E15: N
C16: CGID | D16: NUMBER | E16: Y | G16: The care giver for the chart event.
C17: CUID | D17: NUMBER | E17: Y | G17: The care unit where the chart event took place.
C18: VALUE1 | D18: VARCHAR2 | E18: Y | G18: The first chart event value.
C19: VALUE1NUM | D19: NUMBER | E19: Y | G19: The first chart event value (cast to numeric value).
C20: VALUE1UOM | D20: VARCHAR2 | E20: Y | G20: The units of measurement for the first chart event value.
C21: VALUE2 | D21: VARCHAR2 | E21: Y | G21: The second chart event value.
C22: VALUE2NUM | D22: NUMBER | E22: Y | G22: The second chart event value (cast to numeric value).
C23: VALUE2UOM | D23: VARCHAR2 | E23: Y | G23: The units of measurement for the second chart event value.
C24: RESULTSTATUS | D24: VARCHAR2 | E24: Y
C25: STOPPED | D25: VARCHAR2 | E25: Y
C26: ANNOTATION | D26: VARCHAR2 | E26: Y

Sheet COMORBIDITY_SCORES
A2: Table Name: | D2: COMORBIDITY_SCORES
A3: Description
B4: Patient Comorbidity index for all the secondary disease along with primary
C10: Column Name | D10: Data Type | E10: Nullable | F10: Default value | G10: Comments
C11: subject_id | D11: integer | E11: N | G11: Patienrt identification number
C12: hadm_id | D12: integer | E12: N | G12: Hospital Admission identificatio Number
C13: category | D13: char(10) | E13: Y | F13: Elixhauser | G13: Comorbidity (presence of one or more additional conditions co-occurring with primary health condition) risk adjustment models
C14: congestive_heart_failure | D14: float | E14: Y | G14: Comorbidity risk score corresponding to disease condition
C15: cardiac_arrhythmias | D15: float | E15: Y
C16: valvular_disease | D16: float | E16: Y
C17: pulmonary_circulation | D17: float | E17: Y
C18: peripheral_vascular | D18: float | E18: Y
C19: hypertension | D19: float | E19: Y
C20: paralysis | D20: float | E20: Y
C21: other_neurological | D21: float | E21: Y
C22: chronic_pulmonary | D22: float | E22: Y
C23: diabetes_uncomplicated | D23: float | E23: Y
C24: diabetes_complicated | D24: float | E24: Y
C25: hypothyroidism | D25: float | E25: Y
C26: renal_failure | D26: float | E26: Y
... C43: depression | D43: float | E43: Y

Sheet DELIVERIES
A2: Table Name: | D2: DELIVERIES
A3: Description
B4: Its related to the I/O Events and the details in the table indicates that the rate at which the medication has infused to the patient. Example: D5W (Dextrose) is a form of glucose can be infused to the patients depends on their health condition such as 10 ml/hr or 18.5 ml/hr, etc.,
C10: Column Name | D10: Data Type | E10: Nullable | F10: Default value | G10: Comments
C11: SUBJECT ID | D11: NUMBER | E11: N | G11: The patient for the particular delivery.
C12: IOITEMID | D12: NUMBER | E12: N | G12: The IO item id for the delivery.
C13: CHARTTIME | D13: DATE | E13: N | G13: The chart time of the IO delivery.
C14: ELEMID | D14: NUMBER | E14: N
C15: CGID | D15: NUMBER | E15: Y | G15: The care giver for the delivery.
C16: CUID | D16: NUMBER | E16: Y | G16: The care unit for the delivery.
C17: SITE | D17: VARCHAR2 | E17: Y | G17: The site of the de- livery.
C18: RATE | D18: NUMBER | E18: Y | G18: The delivery rate.
C19: RATEUOM | D19: VARCHAR2 | E19: N | G19: The units of measurement of the rate of delivery.

Sheet DEMOGRAPHIC_DETAIL
A2: Table Name: | D2: DEMOGRAPHIC_DETAIL
A3: Description
B4: Patients demographic details. This details will be captured at the time of admission to any Care units
C10: Column Name | D10: Data Type | E10: Nullable | F10: Default value | G10: Comments
C11: subject_id | D11: integer | E11: N | G11: Patient identificatiom number
C12: hadm_id | D12: integer | E12: N | G12: Hospital admission Id
C13: marital_status_itemid | D13: integer | E13: Y | G13: Marital status code
C14: marital_status_descr | D14: varchar(50) | E14: Y | G14: Marital status description such as "Married", etc.,
C15: ethnicity_itemid | D15: integer | E15: Y | G15: Ethnicity code
C16: ethnicity_descr | D16: varchar(50) | E16: Y | G16: Ethnicity description such as "WHITE", "African American","Hispanic", etc.,
C17: overall_payor_group_itemid | D17: integer | E17: Y | G17: Payor group id
C18: overall_payor_group_descr | D18: varchar(50) | E18: Y | G18: Payor type / description such as "Private", "Govt funded", etc.,
C19: religion_itemid | D19: integer | E19: Y | G19: Religion identification code
C20: religion_descr | D20: varchar(50) | E20: Y | G20: Religion description such as "BUDDHIST", etc.,
C21: admission_type_itemid | D21: integer | E21: Y | G21: Admission identification code
C22: admission_type_descr | D22: varchar(50) | E22: Y | G22: Type of admission such as "Emergency", "Newborn", etc.,
... C24: admission_source_descr | D24: varchar(50) | E24: Y | G24: Admission source. Example - Trasferred from different hospital,MICU to CCU, etc.,

Sheet DEMOGRAPHICEVENTS
A2: Table Name: | D2: DEMOGRAPHICEVENTS
A3: Description
B4: Additional demographic details about the patient such as "Admisison source - HMO referal, Religion - Patient denied to provide, Payor group name - Auto liability, etc.,"
C10: Column Name | D10: Data Type | E10: Nullable | F10: Default value | G10: Comments
C11: subject_id | D11: integer | E11: N | G11: Patient identification Number
C12: hadm_id | D12: integer | E12: N | G12: Patients hospital admission identification number
C13: itemid | D13: integer | E13: N | G13: Item Id denotes the additional details about patient demography

Sheet D_PATIENTS
A2: Table Name: | D2: D_PATIENTS
A3: Description
B4: Defines each SUBJECT_ID in the database, i.e. defines a single patient.
C10: Column Name | D10: Data Type | E10: Nullable | F10: Default value | G10: Comments
C11: SUBJECT ID | D11: NUMBER | E11: N | G11: Table record unique identier, the subject id.
C12: SEX | D12: VARCHAR2 | E12: Y | G12: The patient gender
C13: DOB | D13: DATE | E13: N | G13: The date of birth of the patient

Sheet DRGEVENTS
A2: Table Name: | D2: DRGEVENTS
A3: Description
B4: Drug Related Group is a patient classification system that standardizes prospective payment to hospitals and encourages cost containment initiatives.
C10: Column Name | D10: Data Type | E10: Nullable | F10: Default value | G10: Comments
C11: subject_id | D11: integer | E11: N | G11: Patient identification Number
C12: hadm_id | D12: integer | E12: N | G12: Hospital admission identification number
C13: itemid | D13: integer | E13: N | G13: DRG event id. Example - A number to denote "Chemo therapy"
C14: cost_weight | D14: float | E14: Y | G14: The DRG weight is multiplied by the hospital’s payment rate per case. All hospitals are reimbursed on the basis of one of two Federal rates--“large urban” or “other.

Sheet ICD9
A2: Table Name: | D2: ICD9
A3: Description
B4: Patients diagnosis event details. Example : Diagnosis test related "Iron Deficiency Anemia", etc.,
C10: Column Name | D10: Data Type | E10: Nullable | F10: Default value | G10: Comments
C11: SUBJECT ID | D11: NUMBER | E11: N | G11: The patient for the ICD9 code record.
C12: HADM ID | D12: NUMBER | E12: N | G12: The hospital admission for the ICD9 code record.
C13: SEQUENCE | D13: NUMBER | E13: N | G13: Sequence number / row number of an event
C14: CODE | D14: VARCHAR2 | E14: N | G14: The ICD9 code.
C15: DESCRIPTION | D15: VARCHAR2 | E15: Y | G15: A description of the ICD9 code.

Sheet ICUSTAY_DAYS
A2: Table Name: | D2: ICUSTAY_DAYS
A3: Description
B4: Patients Care unit stay details. Mostly this table helps to calculate total number of care unit stay for a given patient with help of "First" and "Last" day flag(Y/N)
C10: Column Name | D10: Data Type | E10: Nullable | F10: Default value | G10: Comments
C11: icustay_id | D11: integer | G11: A Unique number denotes ICU Stay
C12: subject_id | D12: integer
C13: seq | D13: integer | G13: Sequence number / row number of an event
C14: begintime | D14: timestamp | G14: Data and time of the Care unit event. Usually this will be captured on everyday basis. To get Total number of care unit stay, we have to refer "First day" flag and "Last day" flag and compute the days difference
C15: endtime | D15: timestamp | G15: Data and time of the Care unit event. Usually this will be captured on everyday basis
C16: first_day_flg | D16: char(1) | G16: A flag (Y/N) denotes First day in the care unit
C17: last_day_flg | D17: char(1) | G17: A flag (Y/N) denotes Last day in the care unit

Sheet ICUSTAY_DETAIL
A2: Table Name: | D2: ICUSTAY_DETAIL
A3: Description
B4: Patients care Unit event details. This table will contains hospital admission, discharged, Care unit Admission, discharged, patients age, date of death, etc.,
C10: Column Name | D10: Data Type | E10: Nullable | F10: Default value | G10: Comments
C11: icustay_id | D11: integer | E11: Y | G11: A Unique number denotes ICU Stay
C12: subject_id | D12: integer | E12: Y | G12: Patient identification Number
C13: gender | D13: varchar(1) | E13: Y | G13: Gender code of the Patient
C14: dob | D14: timestamp | E14: N | G14: Date of Birth of the patient
C15: dod | D15: timestamp | E15: Y | G15: Date of Death. Blank / NULL value denotes the patient is alive
C16: expire_flg | D16: varchar(1) | E16: Y | G16: Patients Expire flag. The Value "N" denotes, the patient is alive
C17: subject_icustay_seq | D17: float | E17: Y | G17: Sequence number / row number of an event
C18: hospital_seq | D18: float | E18: Y | G18: Sequence number / row number of an event
C19: icustay_seq | D19: float | E19: Y | G19: Sequence number / row number of an event
C20: hadm_id | D20: integer | E20: Y | G20: The hospital admission for the ICD9 code record.
C21: subject_icustay_total_num | D21: float | E21: Y
C22: hospital_total_num | D22: float | E22: Y
C23: hospital_first_flg | D23: char(1) | E23: Y | G23: A flag (Y/N) denotes the first day of the admission in the hospital
C24: hospital_last_flg | D24: char(1) | E24: Y | G24: A flag (Y/N) denotes the Last day in the hospital
C25: hospital_admit_dt | D25: timestamp | E25: Y | G25: Hospital admission date
C26: hospital_los | D26: float | E26: Y | G26: Length of stay in hospital
C27: hospital_disch_dt | D27: timestamp | E27: Y | G27: Hospital discharged date
C28: hospital_expire_flg | D28: char(1) | E28: Y
C29: icustay_total_num | D29: float | E29: Y
C30: icustay_first_flg | D30: char(1) | E30: Y | G30: A flag (Y/N) denotes first day in the Care Unit
C31: icustay_last_flg | D31: char(1) | E31: Y | G31: A flag (Y/N) denotes Last day in the Care Unit
C32: icustay_intime | D32: timestamp | E32: N | G32: ICU In-time
C33: icustay_outtime | D33: timestamp | E33: N | G33: ICU Out-time
C34: icustay_admit_age | D34: float | E34: Y | G34: Patients age at the time of admission in the Care unit
C35: icustay_age_group | D35: varchar(7) | E35: Y | G35: Patient Age group
C36: icustay_los | D36: float | E36: N | G36: Length of Stay in the care unit
C37: icustay_expire_flg | D37: char(1) | E37: Y | G37: A flag (Y/N) denotes whether the patient expired in the Care unit
C38: icustay_first_careunit | D38: varchar(20) | E38: Y | G38: Care unit in which Patient admitted initially
C39: icustay_last_careunit | D39: varchar(20) | E39: Y | G39: Care unit from which Patient discharged
C40: icustay_first_service | D40: varchar(110) | E40: Y | G40: First day in the Care Unit
C41: icustay_last_service | D41: varchar(110) | E41: Y | G41: Last day in the Care Unit
... C51: sofa_max | D51: float | E51: Y | G51: Maximum SOFA
C52: matched_waveforms_num | D52: float | E52: Y

Sheet ICUSTAYEVENTS
A2: Table Name: | D2: ICUSTAYEVENTS
A3: Description
B4: Patients Care unit stay details are captured in a single line. This table will provide an overview of the patients care unit stay such as "Admission date, discharged date, length of stay, Care unit at the time of admission and discharged, etc.,"
C10: Column Name | D10: Data Type | E10: Nullable | F10: Default value | G10: Comments
C11: icustay_id | D11: integer | E11: N | G11: A Unique number denotes ICU Stay
C12: subject_id | D12: integer | E12: N | G12: Patient identification Number
C13: intime | D13: timestamp | E13: N | G13: Date and Time of the admission in the care unit
C14: outtime | D14: timestamp | E14: N | G14: Date and Time of the discharge the care unit
C15: los | D15: float | E15: N | G15: Total Length of stay in the Care unit (in Minutes)
C16: first_careunit | D16: integer | E16: Y | G16: Care unit ID - At the time of an admission
C17: last_careunit | D17: integer | E17: Y | G17: Care unit ID - At the time of an discharge

Sheet IOEVENTS
A2: Table Name: | D2: IOEVENTS
A3: Description
B4: Patients Input / Output event during their Care unit stay. Example : Type of IV infusions provided to a patient during their ICU stay and start and End time of the IV event
C10: Column Name | D10: Data Type | E10: Nullable | F10: Default value | G10: Comments
C11: SUBJECT_ID | D11: NUMBER | E11: N | G11: The parient for the IO event.
C12: ICUSTAY_ID | D12: NUMBER | E12: N | G12: A Unique number denotes ICU Stay
C13: ITEMID | D13: DATE | E13: N
C14: CHARTTIME | D14: DATE | E14: N | G14: Time of the event
C15: ELEMID | D15: NUMBER | E15: N
C16: ALTID | D16: NUMBER | E16: N
C17: REALTIME | D17: DATE | E17: N
C18: CGID | D18: NUMBER | E18: N | G18: The care giver for the IO event.
C19: CUID | D19: NUMBER | E19: N | G19: The care unit for the IO event.
C20: VOLUME | D20: NUMBER | E20: Y | G20: The volume of the IO event.
C21: VOLUMEUOM | D21: NUMBER | E21: Y | G21: The units of measurement of the volume of the IO event.
C22: UNITSHUNG | D22: NUMBER | E22: Y | G22: Total volume of the unit in the bottle
C23: UNITSHUNGUOM | D23: VARCHAR | E23: Y | G23: The units of measurement of the volume
C24: NEWBOTTLE | D24: VARCHAR | E24: Y
C25: STOPPED | D25: VARCHAR | E25: Y
C26: ESTIMATE | D26: VARCHAR | E26: Y

Sheet LABEVENTS
A2: Table Name: | D2: LABEVENTS
A3: Description
B4: The LABEVENTS data contains information regarding laboratory based measurements. The process for acquiring a lab measurement is as follows: first, a member of the clinical staff acquires a fluid from a site in the patient’s body (e.g. blood from an arterial line, urine from a catheter, etc). Next, the fluid is bar coded to associate it with the patient and timestamped to record the time of the fluid acquisition. The lab analyses the data and returns a result within 4-12 hours.
C10: Column Name | D10: Data Type | E10: Nullable | F10: Default value | G10: Comments
C11: subject_id | D11: integer | E11: N | G11: Patient identification Number
C12: hadm_id | D12: integer | E12: Y | G12: Hospital admission identification Number
C13: icustay_id | D13: integer | E13: Y | G13: A Unique number denotes ICU Stay
C14: itemid | D14: integer | E14: N
C15: charttime | D15: timestamp | E15: N | G15: Date and Time of the Lab Event
C16: value | D16: varchar(100) | E16: Y | G16: Diagnosis test value
C17: valuenum | D17: float | E17: Y | G17: Diagnosis test value
C18: flag | D18: varchar(10) | E18: Y | G18: A flag to denote the result of the test. Example : Abnormal,etc.,
C19: valueuom | D19: varchar(10) | E19: Y | G19: The units of measurement

Sheet MEDEVENTS
A2: Table Name: | D2: MEDEVENTS
A3: Description
B4: Medication(s) given to a patient are recorded in this table.
C10: Column Name | D10: Data Type | E10: Nullable | F10: Default value | G10: Comments
C11: SUBJECT_ID | D11: NUMBER | E11: N | G11: Patient identification Number
C12: ICUSTAY_ID | D12: NUMBER | E12: N | G12: A Unique number denotes ICU Stay
C13: ITEMID | D13: NUMBER | E13: N | G13: The medication item id for the event.
C14: CHARTTIME | D14: DATE | E14: N | G14: The chart time of the medication event.
C15: ELEMID | D15: NUMBER | E15: N
C16: REALTIME | D16: DATE | E16: N
C17: CGID | D17: NUMBER | E17: Y | G17: The care giver for the medication event.
C18: CUID | D18: NUMBER | E18: Y | G18: The care unit for the medication event.
C19: VOLUME | D19: NUMBER | E19: Y | G19: The volume of the medication event.
C20: DOSE | D20: NUMBER | E20: Y | G20: The doseage of the medication event
C21: DOSEUOM | D21: VARCHAR2 | E21: Y | G21: The units of measurement of the doseage of the medication event.
C22: SOLUTIONID | D22: NUMBER | E22: Y | G22: The solution used in the medication event.
C23: SOLVOLUME | D23: NUMBER | E23: Y | G23: The volume of solution used in the medication event.
C24: SOLUNITS | D24: VARCHAR2 | E24: Y | G24: The units of the volume of solution used in the medication event
C25: ROUTE | D25: VARCHAR2 | E25: Y | G25: Medication infuse route (IV, Injection, etc.,)
C26: STOPPED | D26: VARCHAR2 | E26: Y

Sheet MICROBIOLOGYEVENTS
A2: Table Name: | D2: MICROBIOLOGYEVENTS
A3: Description
B4: This table Contains microbiology information, including tests performed and sensitivities
C10: Column Name | D10: Data Type | E10: Nullable | F10: Default value | G10: Comments
C11: subject_id | D11: integer | G11: Patient identification Number
C12: hadm_id | D12: integer | G12: Hospital admission identification Number
C13: charttime | D13: timestamp | G13: The chart time of the Micro bio event.
C14: spec_itemid | D14: integer
C15: org_itemid | D15: integer
C16: isolate_num | D16: float
C17: ab_itemid | D17: integer
C18: dilution_amount | D18: varchar(72)
C19: dilution_comparison | D19: varchar(10)
C20: interpretation | D20: varchar(1)

Sheet NOTEEVENTS
A2: Table Name: | D2: NOTEEVENTS
A3: Description
B4: Clinical Notes for the patients. Usually during the stay in the Care unit, skilled Nurse / Physician will leave a note about the patients health condition. Sometime, critical health information about patients such as Mortaility event, Comorbidity condition, infections,etc. will be captured in the notes
C10: Column Name | D10: Data Type | E10: Nullable | F10: Default value | G10: Comments
C11: SUBJECT ID | D11: NUMBER | E11: N | G11: The patient for the note event.
C12: NOTEID | D12: NUMBER | E12: N | G12: The note item for the event.
C13: ELEMID | D13: NUMBER | E13: N
C14: CHARTTIME | D14: DATE | E14: N | G14: The chart time of the note event.
C15: REALTIME | D15: DATE | E15: N
C16: CGID | D16: NUMBER | E16: Y | G16: The care giver for the note event.
C17: CORRECTION | D17: CHAR | E17: N
C18: CUID | D18: NUMBER | E18: Y | G18: The care unit for the note event.
C19: CATEGORY | D19: VARCHAR2 | E19: Y
C20: TITLE | D20: VARCHAR2 | E20: Y
C21: TEXT | D21: VARCHAR2 | E21: Y | G21: The Text of the note event

Sheet POE_MED
A2: Table Name: | D2: POE_MED
A3: Description
B4: Pharmacy provider order entry (Pharmacy claims) - The medication and the dosage details are captured from the pharmacy
C10: Column Name | D10: Data Type | E10: Nullable | F10: Default value | G10: Comments
C11: POE ID | D11: NUMBER | E11: N | G11: A Unique number to represent POE Event
C12: DRUG TYPE | D12: VARCHAR2 | E12: N | G12: Type of the drug given to the patient ("Main" to address the primary disease and treatment and "Base" is a supportive medications such as D5W, etc.,
C13: DRUG NAME | D13: VARCHAR2 | E13: N | G13: Drug Name (Drug name appears in the bottl / vial, etc.,)
C14: DRUG NAME GENERIC | D14: VARCHAR2 | E14: Y | G14: Generic Name of the Drug
C15: PROD STRENGTH | D15: VARCHAR2 | E15: Y | G15: Strength of the product / drug
C16: FORM RX | D16: VARCHAR2 | E16: Y | G16: Dosage form of the drug (Vial, bottle, etc,)
C17: DOSE VAL RX | D17: VARCHAR2 | E17: Y | G17: Dosage Volume (Total quantity - 200 ml, etc.,)
C18: DOSE UNIT RX | D18: VARCHAR2 | E18: Y | G18: Drug dosage unit (ml, etc.,)
C19: FORM VAL DISP | D19: VARCHAR2 | E19: Y | G19: Dispensed form volume. Example - Out of 200 ml, 50 ml dispensed to the patient per the prescription
C20: FORM UNIT DISP | D20: VARCHAR2 | E20: Y | G20: Dispensed form unit (ml, etc.,)
C21: DOSE VAL DISP | D21: NUMBER | E21: Y | G21: Dispensed Dosage form of the drug (Vial, bottle, etc,)
C22: DOSE UNIT DISP | D22: VARCHAR2 | E22: Y | G22: Dispensed Dosage Volume (Total quantity - 200 ml, etc.,)
C23: DOSE RANGE OVERRIDE | D23: VARCHAR2 | E23: Y | G23: Comments to justify the over dosage of the drug

Sheet POE_ORDER
A2: Table Name: | D2: POE_ORDER
A3: Description
B4: Pharmacy provider order entry (Pharmacy claims) - The medication and the dosage details are captured from the pharmacy - Detailed version of the data captured based on the usage.All the fields are related to POE_MED table
C10: Column Name | D10: Data Type | E10: Nullable | F10: Default value | G10: Comments
C11: POE ID | D11: NUMBER | E11: N
C12: SUBJECT ID | D12: NUMBER | E12: N
C13: HADM ID | D13: NUMBER | E13: N
C14: START DT | D14: DATE | E14: Y
C15: STOP DT | D15: DATE | E15: Y
C16: ENTER DT | D16: DATE | E16: N
C17: MEDICATION | D17: VARCHAR2 | E17: Y
C18: PROCEDURE TYPE | D18: VARCHAR2 | E18: Y
C19: STATUS | D19: VARCHAR2 | E19: Y
C20: ROUTE | D20: VARCHAR2 | E20: Y
C21: FREQUENCY | D21: VARCHAR2 | E21: Y
C22: DISPENSE SCHED | D22: VARCHAR2 | E22: Y
... C36: RNURSE ADD INSTR | D36: VARCHAR2 | E36: Y

Sheet PROCEDUREEVENTS
A2: Table Name: | D2: PROCEDUREEVENTS
A3: Description
B4: Medical Procedure performed to the patients durign their stay. Procedure (Knee Arthroscopy, Oint Biopsy, etc.,) can be performed either prior or after the diagnosis result
C10: Column Name | D10: Data Type | E10: Nullable | F10: Default value | G10: Comments
C11: subject_id | D11: integer | E11: N | G11: The patient for the note event.
C12: hadm_id | D12: integer | E12: N | G12: Hospital admission identification Number
C13: itemid | D13: integer | E13: Y | G13: Item to denote the procedure. Example : Knee Arthroscopy, Oint Biopsy
C14: sequence_num | D14: integer | E14: N | G14: Sequence number / row number of an event
C15: proc_dt | D15: timestamp | E15: Y | G15: Procedure Date
G22: =PROPER(F22)

Sheet TOTALBALEVENTS
A2: Table Name: | D2: TOTALBALEVENTS
A3: Description
B4: Total Fluid balance event
C10: Column Name | D10: Data Type | E10: Nullable | F10: Default value | G10: Comments
C11: SUBJECT_ID | D11: NUMBER | E11: N | G11: The patient for the note event.
C12: ICUSTAY_ID | D12: NUMBER | E12: N | G12: A Unique number denotes ICU Stay
C13: ITEMID | D13: NUMBER | E13: N | G13: Item to represents the event such as D5W drugs is infused thru IV
C14: CHARTTIME | D14: DATE | E14: N | G14: Date and Time of the event
C15: ELEMID | D15: NUMBER | E15: N
C16: REALTIME | D16: DATE | E16: Y | G16: Actual time IV started to infuse to gthe patient. There will be slight different In time between "Charttime" and this variable
C17: CGID | D17: NUMBER | E17: Y | G17: The care giver id related to this event
C18: CUID | D18: NUMBER | E18: Y | G18: The care unit id related to this event
C19: PERVOLUME | D19: NUMBER | E19: Y
C20: CUMVOLUME | D20: NUMBER | E20: Y
C21: ACCUMPERIOD | D21: VARCHAR2 | E21: Y | G21: Accumulation period. Example - Multiple days need this infusion, One time event, etc.,
C22: APPROX | D22: VARCHAR2 | E22: Y
C23: RESET | D23: NUMBER | E23: Y
C24: STOPPED | D24: VARCHAR2 | E24: Y
